interrupt/__init__.py
interrupt/silently.py
interrupt-1.0.1.dist-info/LICENSE
interrupt-1.0.1.dist-info/METADATA
interrupt-1.0.1.dist-info/WHEEL
interrupt-1.0.1.dist-info/top_level.txt
interrupt-1.0.1.dist-info/zip-safe
interrupt-1.0.1.dist-info/RECORD
