Metadata-Version: 2.1
Name: interrupt
Version: 1.0.1
Summary: Interrupt silently
Home-page: https://github.com/lmittmann/interrupt
Author: lmittmann
License: MIT
Keywords: interrupt
Platform: UNKNOWN
Classifier: Development Status :: 5 - Production/Stable
Classifier: Intended Audience :: Developers
Classifier: License :: OSI Approved :: MIT License
Classifier: Natural Language :: English
Classifier: Programming Language :: Python :: 3
Classifier: Programming Language :: Python :: 3.5
Classifier: Programming Language :: Python :: 3.6
Classifier: Programming Language :: Python :: 3.7
Classifier: Programming Language :: Python :: 3.8
Requires-Python: >=3
